qlm/__init__.py
qlm/commands/__init__.py
qlm/commands/_add.py
qlm/commands/_config.py
qlm/commands/_connect.py
qlm/commands/_create.py
qlm/commands/_download.py
qlm/commands/_edit.py
qlm/commands/_get.py
qlm/commands/_list.py
qlm/commands/_offline.py
qlm/commands/_publish.py
qlm/commands/_remove.py
qlm/commands/_show.py
qlm/github/__init__.py
qlm/github/integrations.py
qlm/main.py
qlm/tools/__init__.py
qlm/tools/config.json
qlm/tools/config_helpers.py
qlm/tools/files.py
qlm/validators/__init__.py
qlm/validators/config.py
qlm/validators/files.py
qlm/validators/github.py
qlm-0.0.3.dist-info/entry_points.txt
qlm-0.0.3.dist-info/LICENSE
qlm-0.0.3.dist-info/WHEEL
qlm-0.0.3.dist-info/METADATA
qlm-0.0.3.dist-info/RECORD
